
{
  "PatientInformation": {
    "name": "John Doe",
    "age": 48,
    "gender": "Male",
    "date_of_birth": "1995-01-01",
    "ethnicity": "Hispanic",
    "address": "123 Main St, Anytown, USA 12345",
    "phone_number": "555-1234",
    "email": "johndoe@example.com",
    "social_security_number": "123-45-6789"
  },
  "VisitDetails": {
    "date_of_visit": "2019-01-01",
    "primary_complaints": "Burning sensation in eyes, dry mouth, and weakness",
    "symptoms": [
      "Burning sensation in eyes",
      "Dry mouth",
      "Weakness"
    ]
  },
  "MedicalHistory": {
    "past_medical_history": [
      {
        "name": "Rheumatoid Arthritis",
        "diagnosis_date": "2018-01-01",
        "symptoms": [
          "Joint pain and weakness"
        ]
      },
      {
        "name": "Autoimmune diseases",
        "diagnosis_date": "2018-01-01",
        "symptoms": [
          "Fatigue and joint pain"
        ]
      }
    ],
    "surgical_history": [],
    "family_history": {
      "father": {
        "name": "John Sr.",
        "diagnosis_date": "2015-01-01",
        "symptoms": [
          "High blood pressure"
        ]
      },
      "mother": {
        "name": "Jane Sr.",
        "diagnosis_date": "2010-01-01",
        "symptoms": [
          "Hypothyroidism"
        ]
      }
    },
    "known_allergies": []
  },
  "Medications": [
    {
      "name": "Ibuprofen",
      "dosage": "200mg every 4-6 hours",
      "frequency": "As needed"
    },
    {
      "name": "NSAIDs",
      "dosage": "Acetaminophen 650mg every 4-6 hours",
      "frequency": "As needed"
    }
  ],
  "TestResults": [
    {
      "test_name": "Complete Blood Count (CBC)",
      "date": "2019-01-01",
      "results": [
        {
          "value": 14.5,
          "unit": "g/dL"
        },
        {
          "value": 3.7,
          "unit": "g/dL"
        }
      ]
    },
    {
      "test_name": "Lactate Dehydrogenase (LDH)",
      "date": "2019-01-01",
      "results": [
        {
          "value": 333,
          "unit": "U/L"
        }
      ]
    },
    {
      "test_name": "Creatinine Kinase (CK)",
      "date": "2019-01-01",
      "results": [
        {
          "value": 229,
          "unit": "U/L"
        }
      ]
    },
    {
      "test_name": "Hemoglobin",
      "date": "2019-01-01",
      "results": [
        {
          "value": 13.9,
          "unit": "g/dL"
        }
      ]
    },
    {
      "test_name": "Hematocrit",
      "date": "2019-01-01",
      "results": [
        {
          "value": 41.3,
          "unit": "%"
        }
      ]
    }
  ],
  "Diagnosis": "Sjögren's Syndrome",
  "TreatmentPlan": [
    {
      "prescribed_treatment": "Corticosteroids",
      "dosage": "10mg daily",
      "frequency": "As needed"
    },
    {
      "prescribed_treatment": "Hydrochloroquine",
      "dosage": "50mg daily",
      "frequency": "As needed"
    }
  ],
  "PhysicalExamination": {
    "vitals": {
      "temperature": 98.5,
      "heart_rate": 68,
      "blood_pressure": "126/85",
      "respiratory_rate": 16
    },
    "physical_findings": [
      {
        "location": "Pre-auricular area",
        "description": "Macular rash"
      },
      {
        "location": "Knees and hands",
        "description": "Joint pain and swelling"
      }
    ]
  },
  "SpecialistConsultations": [
    {
      "specialist_name": "Dr. Smith",
      "specialist_referral": "Primary Care Physician"
    },
    {
      "specialist_name": "Dr. Johnson",
      "specialist_referral": "Rheumatologist"
    }
  ],
  "SocialandLifestyleInformation": {
    "habits": {
      "smoking": "None",
      "drinking": "None",
      "diet": "Well-nourished"
    },
    "occupation": "Electrician",
    "dietary_notes": "High school graduate, working as an electrician",
    "lifestyle": {
      "physical_exertion": "Daily physical exertion",
      "weight": "Overweight BMI",
      "back_pain": "Back pain"
    }
  },
  "VaccinationRecords": [],
  "MentalHealthNotes": {
    "observations": [
      "Stress and anxiety"
    ],
    "recommendations": [
      "Reduce stress and anxiety"
    ]
  },
  "FutureAppointmentsandFollowUps": [
    {
      "appointment_date": "2020-01-01",
      "suggested_tests": [
        "Complete Blood Count (CBC)",
        "Lactate Dehydrogenase (LDH)"
      ]
    },
    {
      "appointment_date": "2020-02-01",
      "suggested_tests": [
        "Complete Blood Count (CBC)",
        "Creatinine Kinase (CK)"
      ]
    }
  ],
  "Correlations": [
    {
      "symptoms": "Chronic fatigue linked to borderline Vitamin B12 levels",
      "diagnostic_findings": "Vitamin B12 deficiency"
    },
    {
      "test_results": "Elevated cholesterol levels correlate with family history of ischemic heart disease",
      "family_history": "Yes"
    },
    {
      "medications": "Prescribed NSAIDs avoided due to history of ibuprofen-related gastrointestinal distress",
      "allergies": "None"
    }
  ]
}
